keboola/component/__init__.py
keboola/component/base.py
keboola/component/dao.py
keboola/component/exceptions.py
keboola/component/interface.py
keboola/component/sync_actions.py
keboola/component/table_schema.py
keboola_component-1.8.3.dist-info/licenses/LICENSE
keboola_component-1.8.3.dist-info/METADATA
keboola_component-1.8.3.dist-info/WHEEL
keboola_component-1.8.3.dist-info/top_level.txt
keboola_component-1.8.3.dist-info/RECORD
