Metadata-Version: 2.4
Name: keboola.component
Version: 1.8.3
Summary: General library for Python applications running in Keboola Connection environment
Author-email: Keboola KDS Team <support@keboola.com>
License-Expression: MIT
Project-URL: Documentation, https://keboola.github.io/python-component/interface.html
Project-URL: Repository, https://github.com/keboola/python-component
Project-URL: Component Template project, https://github.com/keboola/cookiecutter-python-component
Classifier: Programming Language :: Python :: 3
Classifier: Programming Language :: Python :: 3.8
Classifier: Programming Language :: Python :: 3.9
Classifier: Programming Language :: Python :: 3.10
Classifier: Programming Language :: Python :: 3.11
Classifier: Programming Language :: Python :: 3.12
Classifier: Programming Language :: Python :: 3.13
Classifier: Programming Language :: Python :: 3.14
Classifier: Operating System :: OS Independent
Classifier: Intended Audience :: Developers
Classifier: Intended Audience :: Information Technology
Classifier: Intended Audience :: Education
Classifier: Topic :: Software Development :: Libraries
Classifier: Topic :: Software Development :: Libraries :: Python Modules
Classifier: Development Status :: 5 - Production/Stable
Requires-Python: >=3.8
License-File: LICENSE
Requires-Dist: pygelf
Requires-Dist: pytz<2021.0
Requires-Dist: deprecated
Dynamic: license-file
